ucop_util/__init__.py
ucop_util/athena_util.py
ucop_util/date_handler.py
ucop_util/file_name_parser.py
ucop_util/job_run_waiter.py
ucop_util/lf_perms_helper.py
ucop_util/marker_file_helper.py
ucop_util/ref_data_file_name_parser.py
ucop_util/ref_data_queue_helper.py
ucop_util/running_stacks_info.py
ucop_util/send_mail_helper.py
ucop_util/stack_info.py
ucop_util/util_exception.py
ucop_util/workflow_initiator.py
ucop_util_pkg-2.0.7.dist-info/licenses/LICENSE
ucop_util_pkg-2.0.7.dist-info/METADATA
ucop_util_pkg-2.0.7.dist-info/WHEEL
ucop_util_pkg-2.0.7.dist-info/top_level.txt
ucop_util_pkg-2.0.7.dist-info/RECORD
