Metadata-Version: 2.4
Name: ucop-util-pkg
Version: 2.0.7
Summary: UCOP utilities package for the AWS Data Lake projects.
Home-page: https://github.com/sdsc-sherlock/rdms/tree/main/ucop-util-pkg
Download-URL: https://test.pypi.org/search/?q=ucop-util-pkg
Author: Hooman Pejman
Author-email: Hooman.Pejman@ucop.edu
License: Completely unsupported freeware.
Classifier: Topic :: Software Development :: Libraries :: Python Modules
Classifier: Programming Language :: Python :: 3
Classifier: Programming Language :: Python :: 3.6
Classifier: Programming Language :: Python :: Implementation :: CPython
Classifier: Programming Language :: Python :: Implementation :: PyPy
Requires-Python: >=3.8
License-File: LICENSE
Dynamic: author
Dynamic: author-email
Dynamic: classifier
Dynamic: description
Dynamic: description-content-type
Dynamic: download-url
Dynamic: home-page
Dynamic: license
Dynamic: license-file
Dynamic: requires-python
Dynamic: summary
